portage-stubs/__init__.pyi
portage-stubs/py.typed
portage-stubs/versions.pyi
portage_types-0.0.2.dist-info/LICENSE.txt
portage_types-0.0.2.dist-info/METADATA
portage_types-0.0.2.dist-info/WHEEL
portage_types-0.0.2.dist-info/RECORD
