Metadata-Version: 2.1
Name: portage-types
Version: 0.0.2
Summary: Typing stubs for Portage
License: MIT
Author: Andrew Udvare
Author-email: audvare@gmail.com
Requires-Python: >=3.10,<4
Classifier: License :: OSI Approved :: MIT License
Classifier: Programming Language :: Python :: 3
Classifier: Programming Language :: Python :: 3.10
Classifier: Programming Language :: Python :: 3.11
Classifier: Typing :: Typed
